hikari_clusters/__init__.py
hikari_clusters/__main__.py
hikari_clusters/base_client.py
hikari_clusters/brain.py
hikari_clusters/callbacks.py
hikari_clusters/close_codes.py
hikari_clusters/cluster.py
hikari_clusters/commands.py
hikari_clusters/events.py
hikari_clusters/exceptions.py
hikari_clusters/info_classes.py
hikari_clusters/ipc_base.py
hikari_clusters/ipc_client.py
hikari_clusters/ipc_server.py
hikari_clusters/payload.py
hikari_clusters/py.typed
hikari_clusters/server.py
hikari_clusters/task_manager.py
hikari_clusters-1.2.0.dist-info/LICENSE
hikari_clusters-1.2.0.dist-info/METADATA
hikari_clusters-1.2.0.dist-info/WHEEL
hikari_clusters-1.2.0.dist-info/RECORD
