Metadata-Version: 2.1
Name: hikari-clusters
Version: 1.2.0
Summary: An advanced yet easy-to-use clustering tool for Hikari.
Home-page: https://github.com/TrigonDev/hikari-clusters
License: MIT
Keywords: hikari,discord,clustering,bot,ipc
Author: Circuit
Requires-Python: >=3.9,<3.14
Classifier: License :: OSI Approved :: MIT License
Classifier: Programming Language :: Python :: 3
Classifier: Programming Language :: Python :: 3.9
Classifier: Programming Language :: Python :: 3.10
Classifier: Programming Language :: Python :: 3.11
Classifier: Programming Language :: Python :: 3.12
Requires-Dist: hikari (>=2.0.0,<3.0.0)
Requires-Dist: pytest-cov (>=3,<5)
Requires-Dist: websockets (>=11.0,<12.0)
Project-URL: Documentation, https://github.com/TrigonDev/hikari-clusters/wiki
Project-URL: Repository, https://github.com/TrigonDev/hikari-clusters
